proxy6net_api/__init__.py
proxy6net_api/api.py
proxy6net_api/config.py
proxy6net_api/errors.py
proxy6net_api/types.py
proxy6net_api/utils.py
proxy6net_api-1.0.0.dist-info/LICENSE
proxy6net_api-1.0.0.dist-info/METADATA
proxy6net_api-1.0.0.dist-info/WHEEL
proxy6net_api-1.0.0.dist-info/top_level.txt
proxy6net_api-1.0.0.dist-info/RECORD
