Metadata-Version: 2.1
Name: proxy6net-api
Version: 1.0.0
Summary: Proxy6 API wrapper
Author-email: Nikita Bulavinov <jktujgxtu@gmail.com>
License: MIT License
Project-URL: Homepage, https://github.com/jktujg/proxy6net-api
Project-URL: Bug Tracker, https://github.com/jktujg/proxy6net-api/issues
Keywords: api,wrapper,proxy
Classifier: License :: OSI Approved :: MIT License
Classifier: Operating System :: OS Independent
Classifier: Programming Language :: Python :: 3.11
Classifier: Programming Language :: Python :: 3.12
Requires-Python: >=3.11
License-File: LICENSE
Requires-Dist: pydantic ==2.6.3
Requires-Dist: Requests ==2.31.0
